google_flight_scraper/__init__.py
google_flight_scraper/driver.py
google_flight_scraper/flight.py
google_flight_scraper/query.py
google_flight_scraper/scraper.py
google_flight_scraper-0.2.0.dist-info/LICENSE
google_flight_scraper-0.2.0.dist-info/METADATA
google_flight_scraper-0.2.0.dist-info/WHEEL
google_flight_scraper-0.2.0.dist-info/RECORD
