Metadata-Version: 2.1
Name: google-flight-scraper
Version: 0.2.0
Summary: A library to scrape and analyze Google Flight data
License: MIT
Author: Kadri
Author-email: knizam@psu.edu
Requires-Python: >=3.10,<3.13
Classifier: License :: OSI Approved :: MIT License
Classifier: Programming Language :: Python :: 3
Classifier: Programming Language :: Python :: 3.10
Classifier: Programming Language :: Python :: 3.11
Classifier: Programming Language :: Python :: 3.12
Requires-Dist: numpy (>=1.26.1,<2.0.0)
Requires-Dist: pandas (>=2.1.1,<3.0.0)
Requires-Dist: price-parser (>=0.3.4,<0.4.0)
Requires-Dist: selenium (>=4.14.0,<5.0.0)
Requires-Dist: strenum (>=0.4.15,<0.5.0)
Requires-Dist: tqdm (>=4.66.1,<5.0.0)
Requires-Dist: webdriver-manager (>=4.0.1,<5.0.0)
